4-bit_counter/counter.v
module counter ( input clk,
                 input rstn,
                 output reg [3:0] out);

    always @ (posedge clk) begin
        if ( !rstn)
            out <= 0;
        else
            out <= out + 1;
    end
endmodule

4-bit_counter/tb.v
module tb_counter;
    reg clk;
    reg rstn;
    wire [3:0] out;


    counter c0 ( .clk(clk),
                  .rstn(rstn),
                  .out(out));

    always #5 clk = ~clk;

    initial begin
        clk <= 0;
        rstn <= 0;

        #20 rstn <= 1;
        #80 rstn <= 0;
        #50 rstn <= 1;

        #20 $finish;

    end

    initial begin
        $dumpfile("counter_wave.vcd");
        $dumpvars(0, tb_counter);
    end

endmodule

4-bit_counter/counter_wave.vcd
$date
	Sun Aug  8 15:06:07 2021
$end
$version
	Icarus Verilog
$end
$timescale
	1s
$end
$scope module tb_counter $end
$var wire 4 ! out [3:0] $end
$var reg 1 " clk $end
$var reg 1 # rstn $end
$scope module c0 $end
$var wire 1 " clk $end
$var wire 1 # rstn $end
$var reg 4 $ out [3:0] $end
$upscope $end
$upscope $end
$enddefinitions $end
#0
$dumpvars
bx $
0#
0"
bx !
$end
#5
b0 !
b0 $
1"
#10
0"
#15
1"
#20
1#
0"
#25
b1 !
b1 $
1"
#30
0"
#35
b10 !
b10 $
1"
#40
0"
#45
b11 !
b11 $
1"
#50
0"
#55
b100 !
b100 $
1"
#60
0"
#65
b101 !
b101 $
1"
#70
0"
#75
b110 !
b110 $
1"
#80
0"
#85
b111 !
b111 $
1"
#90
0"
#95
b1000 !
b1000 $
1"
#100
0#
0"
#105
b0 !
b0 $
1"
#110
0"
#115
1"
#120
0"
#125
1"
#130
0"
#135
1"
#140
0"
#145
1"
#150
1#
0"
#155
b1 !
b1 $
1"
#160
0"
#165
b10 !
b10 $
1"
