mod_N_counter/modN.v
module modN_ctr
    #(parameter N = 10,
      parameter WIDTH = 4)
    (
        input clk,
        input rstn,
        output reg [WIDTH-1:0] out
    );
    
    always @ (posedge clk) begin
        if (!rstn) begin
            out <= 0;
        end else begin
            if (out == N-1)
                out <= 0;
            else
                out <= out + 1;
        end    
    end

endmodule

mod_N_counter/tb.v
module tb;
    parameter N = 10;
    parameter WIDTH = 4;

    reg clk;
    reg rstn;
    wire [WIDTH-1 : 0] out;

    modN_ctr u0 ( .clk(clk),
                   .rstn(rstn),
                   .out(out));

    always #10 clk = ~clk;

    initial begin
        {clk, rstn} <= 0;

        $monitor ("T=%0t rstn=%0b out=0x%0h", $time, rstn, out);
        repeat(2) @ (posedge clk);
        rstn <= 1;

        repeat(20) @ (posedge clk);
        $finish;
    end

    initial begin
        $dumpfile("modN_wave.vcd");
        $dumpvars(0, tb);
    end

endmodule

mod_N_counter/modN_wave.vcd
$date
	Sun Aug  8 15:48:22 2021
$end
$version
	Icarus Verilog
$end
$timescale
	1s
$end
$scope module tb $end
$var wire 4 ! out [3:0] $end
$var reg 1 " clk $end
$var reg 1 # rstn $end
$scope module u0 $end
$var wire 1 " clk $end
$var wire 1 # rstn $end
$var reg 4 $ out [3:0] $end
$upscope $end
$upscope $end
$enddefinitions $end
#0
$dumpvars
bx $
0#
0"
bx !
$end
#10
b0 !
b0 $
1"
#20
0"
#30
1#
1"
#40
0"
#50
b1 !
b1 $
1"
#60
0"
#70
b10 !
b10 $
1"
#80
0"
#90
b11 !
b11 $
1"
#100
0"
#110
b100 !
b100 $
1"
#120
0"
#130
b101 !
b101 $
1"
#140
0"
#150
b110 !
b110 $
1"
#160
0"
#170
b111 !
b111 $
1"
#180
0"
#190
b1000 !
b1000 $
1"
#200
0"
#210
b1001 !
b1001 $
1"
#220
0"
#230
b0 !
b0 $
1"
#240
0"
#250
b1 !
b1 $
1"
#260
0"
#270
b10 !
b10 $
1"
#280
0"
#290
b11 !
b11 $
1"
#300
0"
#310
b100 !
b100 $
1"
#320
0"
#330
b101 !
b101 $
1"
#340
0"
#350
b110 !
b110 $
1"
#360
0"
#370
b111 !
b111 $
1"
#380
0"
#390
b1000 !
b1000 $
1"
#400
0"
#410
b1001 !
b1001 $
1"
#420
0"
#430
b0 !
b0 $
1"
