D Flip Flop/d_ff.v
module dff (    input d,
                input rstn,
                input clk,
                output reg q);
    
    always @ (posedge clk or negedge rstn)
        if(!rstn)
            q <= 0;
        else
            q <= d;
endmodule

D Flip Flop/d_tb.v
module tb_dff;
    reg clk;
    reg d;
    reg rstn;
    reg [2:0] delay;

    integer i;

    dff dff0 ( .d(d),
                .rstn(rstn),
                .clk(clk),
                .q(q));

    always #10 clk = ~clk;

    initial begin
        clk <= 0;
        d <= 0;
        rstn <= 0;

        #15 d <= 1;
        #10 rstn <= 1;
        for ( i = 0 ; i < 5 ; i = i + 1) begin
            delay = $random;
            #(delay) d <= 1;
        end

        #40 $finish;
    end

    initial begin
        $dumpfile("d_ff_wave.vcd");
        $dumpvars(0, tb_dff);
    end

endmodule

D Flip Flop/d_ff_wave.vcd
$date
	Fri Aug  6 22:55:29 2021
$end
$version
	Icarus Verilog
$end
$timescale
	1s
$end
$scope module tb_dff $end
$var wire 1 ! q $end
$var reg 1 " clk $end
$var reg 1 # d $end
$var reg 3 $ delay [2:0] $end
$var reg 1 % rstn $end
$var integer 32 & i [31:0] $end
$scope module dff0 $end
$var wire 1 " clk $end
$var wire 1 # d $end
$var wire 1 % rstn $end
$var reg 1 ! q $end
$upscope $end
$upscope $end
$enddefinitions $end
#0
$dumpvars
bx &
0%
bx $
0#
0"
0!
$end
#10
1"
#15
1#
#20
0"
#25
1%
b100 $
b0 &
#29
b1 $
b1 &
#30
1!
b10 &
1"
#31
b11 $
b11 &
#34
b101 $
b100 &
#39
b101 &
